ciecam02/__init__.py
ciecam02/colorconvert.py
ciecam02-1.0.6.dist-info/METADATA
ciecam02-1.0.6.dist-info/RECORD
ciecam02-1.0.6.dist-info/WHEEL
ciecam02-1.0.6.dist-info/top_level.txt
