Metadata-Version: 2.1
Name: ciecam02
Version: 1.0.6
Summary: An easy fast transformer between rgb and ciecam02 color space.
Home-page: https://github.com/dannyvi/ciecam02
Author: Dannyvi
Author-email: dannyvis@icloud.com
License: UNKNOWN
Platform: UNKNOWN
Classifier: Programming Language :: Python :: 3
Classifier: License :: OSI Approved :: MIT License
Classifier: Operating System :: OS Independent
Requires-Dist: numpy (>=1.7.1)
